MANIFEST.in
readme.md
setup.py
monkeytype_sqlalchemy/__init__.py
monkeytype_sqlalchemy/config.py
monkeytype_sqlalchemy/store.py
monkeytype_sqlalchemy.egg-info/PKG-INFO
monkeytype_sqlalchemy.egg-info/SOURCES.txt
monkeytype_sqlalchemy.egg-info/dependency_links.txt
monkeytype_sqlalchemy.egg-info/requires.txt
monkeytype_sqlalchemy.egg-info/top_level.txt