Metadata-Version: 2.1
Name: monkeytype-sqlalchemy
Version: 0.1
Summary: A SQLAlchemy backed call trace store for MonkeyType
Home-page: https://github.com/DisruptiveLabs/MonkeyType_SQLAlchemy
Author: Disruptive Labs
Author-email: oss+monkeytype_sqlalchemy@comanage.com
License: BSD
Platform: UNKNOWN
Classifier: Development Status :: 5 - Production/Stable
Classifier: Intended Audience :: Developers
Classifier: License :: OSI Approved :: BSD License
Classifier: Operating System :: OS Independent
Classifier: Programming Language :: Python
Classifier: Programming Language :: Python :: 3
Classifier: Programming Language :: Python :: 3.6
Classifier: Programming Language :: Python :: 3.7
